streamlit_circular_progress_component/__init__.py
streamlit_circular_progress_component/frontend/build/asset-manifest.json
streamlit_circular_progress_component/frontend/build/bootstrap.min.css
streamlit_circular_progress_component/frontend/build/bootstrap.min.css.map
streamlit_circular_progress_component/frontend/build/index.html
streamlit_circular_progress_component/frontend/build/precache-manifest.e8cc11d83d2d667ef923a256c4a52389.js
streamlit_circular_progress_component/frontend/build/service-worker.js
streamlit_circular_progress_component/frontend/build/static/js/2.000e5c0f.chunk.js
streamlit_circular_progress_component/frontend/build/static/js/2.000e5c0f.chunk.js.LICENSE.txt
streamlit_circular_progress_component/frontend/build/static/js/2.000e5c0f.chunk.js.map
streamlit_circular_progress_component/frontend/build/static/js/main.32e2e26f.chunk.js
streamlit_circular_progress_component/frontend/build/static/js/main.32e2e26f.chunk.js.map
streamlit_circular_progress_component/frontend/build/static/js/runtime-main.af1ee0c6.js
streamlit_circular_progress_component/frontend/build/static/js/runtime-main.af1ee0c6.js.map
streamlit_circular_progress_component-0.0.2.dist-info/LICENSE
streamlit_circular_progress_component-0.0.2.dist-info/METADATA
streamlit_circular_progress_component-0.0.2.dist-info/WHEEL
streamlit_circular_progress_component-0.0.2.dist-info/top_level.txt
streamlit_circular_progress_component-0.0.2.dist-info/RECORD
